eqlib.cp38-win_amd64.pyd
eqlib-0.39.0.dist-info/LICENSE
eqlib-0.39.0.dist-info/METADATA
eqlib-0.39.0.dist-info/WHEEL
eqlib-0.39.0.dist-info/top_level.txt
eqlib-0.39.0.dist-info/RECORD
